GCD/GCD.vhdl
library IEEE;
use IEEE.STD_LOGIC_1164.ALL;
use IEEE.NUMERIC_STD.ALL;

entity GCD is
    Port (
        NUM1, NUM2 : in  std_logic_vector(7 downto  0);
        CLK         : in  std_logic;
        RESET       : in  std_logic;
        START       : in  std_logic;
        DONE        : out std_logic;
        RESULT      : out std_logic_vector(7 downto  0)
    );
end GCD;

architecture Behavioral of GCD is
    -- Signals for internal operations
    signal a, b : unsigned(7 downto  0);
    signal temp : unsigned(7 downto  0);
    signal done_internal : std_logic;
begin
    -- Main process for GCD calculation
    process(CLK)
    begin
        if rising_edge(CLK) then
            if RESET = '1' then
                done_internal <= '0';
                a <= (others => '0');
                b <= (others => '0');
            elsif START = '1' then
                a <= unsigned(NUM1);
                b <= unsigned(NUM2);
                done_internal <= '0';
            elsif done_internal = '0' then
                if a = b then
                    RESULT <= std_logic_vector(a);
                    done_internal <= '1';
                elsif a < b then
                    b <= b - a;
                else
                    a <= a - b;
                end if;
            end if;
        end if;
	DONE <= done_internal;
    end process;
end Behavioral;

GCD/GCD_Testbench.vhdl
library IEEE;
use IEEE.STD_LOGIC_1164.ALL;
use IEEE.NUMERIC_STD.ALL;

entity GCD_TB is
end GCD_TB;

architecture behavior of GCD_TB is
    signal NUM1, NUM2 : std_logic_vector(7 downto  0);
    signal CLK, RESET, START, DONE : std_logic;
    signal RESULT : std_logic_vector(7 downto  0);
    
    -- Define a clock period
    constant CLK_PERIOD : time :=  10 ns;
begin
    -- Instantiate the unit under test (UUT)
    UUT: entity work.GCD
        port map (
            NUM1 => NUM1,
            NUM2 => NUM2,
            CLK => CLK,
            RESET => RESET,
            START => START,
            DONE => DONE,
            RESULT => RESULT
        );

    -- Clock generation
    CLK_process : process
    begin
        CLK <= '0';
        wait for CLK_PERIOD /  2;
        CLK <= '1';
        wait for CLK_PERIOD /  2;
    end process;

    -- Stimulus process
    stim_proc: process
    begin
        -- Initialize and hold reset state
        RESET <= '1';
        START <= '0';
        wait for CLK_PERIOD *  10;
        
        -- Release reset and provide inputs
        RESET <= '0';
        NUM1 <= "01000001"; --  65 in binary
        NUM2 <= "01000011"; --  67 in binary
        START <= '1';
        wait for CLK_PERIOD *  10;
        START <= '0';
        
        -- Wait for DONE signal
        wait until DONE = '1';
        
        -- Assert the result
        assert RESULT = "00000001" report "Test failed!" severity error;
        
        -- Stop the simulation
        wait;
    end process;
end behavior;

GCD/result.vcd
$date
  Mon Feb 19 20:54:38 2024
$end
$version
  GHDL v0
$end
$timescale
  1 fs
$end
$scope module standard $end
$upscope $end
$scope module std_logic_1164 $end
$upscope $end
$scope module numeric_std $end
$upscope $end
$scope module gcd_tb $end
$var reg 8 ! num1[7:0] $end
$var reg 8 " num2[7:0] $end
$var reg 1 # clk $end
$var reg 1 $ reset $end
$var reg 1 % start $end
$var reg 1 & done $end
$var reg 8 ' result[7:0] $end
$scope module uut $end
$var reg 8 ( num1[7:0] $end
$var reg 8 ) num2[7:0] $end
$var reg 1 * clk $end
$var reg 1 + reset $end
$var reg 1 , start $end
$var reg 1 - done $end
$var reg 8 . result[7:0] $end
$var reg 8 / a[7:0] $end
$var reg 8 0 b[7:0] $end
$var reg 8 1 temp[7:0] $end
$var reg 1 2 done_internal $end
$upscope $end
$upscope $end
$enddefinitions $end
#0
bUUUUUUUU !
bUUUUUUUU "
0#
1$
0%
U&
bUUUUUUUU '
bUUUUUUUU (
bUUUUUUUU )
0*
1+
0,
U-
bUUUUUUUU .
bUUUUUUUU /
bUUUUUUUU 0
bUUUUUUUU 1
U2
#5000000
1#
1*
b00000000 /
b00000000 0
02
#10000000
0#
0&
0*
0-
#15000000
1#
1*
#20000000
0#
0*
#25000000
1#
1*
#30000000
0#
0*
#35000000
1#
1*
#40000000
0#
0*
#45000000
1#
1*
#50000000
0#
0*
#55000000
1#
1*
#60000000
0#
0*
#65000000
1#
1*
#70000000
0#
0*
#75000000
1#
1*
#80000000
0#
0*
#85000000
1#
1*
#90000000
0#
0*
#95000000
1#
1*
#100000000
b01000001 !
b01000011 "
0#
0$
1%
b01000001 (
b01000011 )
0*
0+
1,
#105000000
1#
1*
b01000001 /
b01000011 0
#110000000
0#
0*
#115000000
1#
1*
#120000000
0#
0*
#125000000
1#
1*
#130000000
0#
0*
#135000000
1#
1*
#140000000
0#
0*
#145000000
1#
1*
#150000000
0#
0*
#155000000
1#
1*
#160000000
0#
0*
#165000000
1#
1*
#170000000
0#
0*
#175000000
1#
1*
#180000000
0#
0*
#185000000
1#
1*
#190000000
0#
0*
#195000000
1#
1*
#200000000
0#
0%
0*
0,
#205000000
1#
1*
b00000010 0
#210000000
0#
0*
#215000000
1#
1*
b00111111 /
#220000000
0#
0*
#225000000
1#
1*
b00111101 /
#230000000
0#
0*
#235000000
1#
1*
b00111011 /
#240000000
0#
0*
#245000000
1#
1*
b00111001 /
#250000000
0#
0*
#255000000
1#
1*
b00110111 /
#260000000
0#
0*
#265000000
1#
1*
b00110101 /
#270000000
0#
0*
#275000000
1#
1*
b00110011 /
#280000000
0#
0*
#285000000
1#
1*
b00110001 /
#290000000
0#
0*
#295000000
1#
1*
b00101111 /
#300000000
0#
0*
#305000000
1#
1*
b00101101 /
#310000000
0#
0*
#315000000
1#
1*
b00101011 /
#320000000
0#
0*
#325000000
1#
1*
b00101001 /
#330000000
0#
0*
#335000000
1#
1*
b00100111 /
#340000000
0#
0*
#345000000
1#
1*
b00100101 /
#350000000
0#
0*
#355000000
1#
1*
b00100011 /
#360000000
0#
0*
#365000000
1#
1*
b00100001 /
#370000000
0#
0*
#375000000
1#
1*
b00011111 /
#380000000
0#
0*
#385000000
1#
1*
b00011101 /
#390000000
0#
0*
#395000000
1#
1*
b00011011 /
#400000000
0#
0*
#405000000
1#
1*
b00011001 /
#410000000
0#
0*
#415000000
1#
1*
b00010111 /
#420000000
0#
0*
#425000000
1#
1*
b00010101 /
#430000000
0#
0*
#435000000
1#
1*
b00010011 /
#440000000
0#
0*
#445000000
1#
1*
b00010001 /
#450000000
0#
0*
#455000000
1#
1*
b00001111 /
#460000000
0#
0*
#465000000
1#
1*
b00001101 /
#470000000
0#
0*
#475000000
1#
1*
b00001011 /
#480000000
0#
0*
#485000000
1#
1*
b00001001 /
#490000000
0#
0*
#495000000
1#
1*
b00000111 /
#500000000
0#
0*
#505000000
1#
1*
b00000101 /
#510000000
0#
0*
#515000000
1#
1*
b00000011 /
#520000000
0#
0*
#525000000
1#
1*
b00000001 /
#530000000
0#
0*
#535000000
1#
1*
b00000001 0
#540000000
0#
0*
#545000000
1#
b00000001 '
1*
b00000001 .
12
#550000000
0#
1&
0*
1-
