JK/jk.vhdl
library IEEE;
use IEEE.STD_LOGIC_1164.ALL;

entity JK_Flip_Flop is
    Port ( J : in  STD_LOGIC;
           K : in  STD_LOGIC;
           CLK : in  STD_LOGIC;
           RST : in  STD_LOGIC;
           Q : out  STD_LOGIC);
end JK_Flip_Flop;

architecture Behavioral of JK_Flip_Flop is

signal temp:std_logic:='0';
begin

process(RST,CLK,J,K)
begin
if(RST='0') then
TEMP<='0';
elsif (CLK ='1') then
if(J='0' and J='0') then
TEMP<=TEMP;
elsif(J='0' and J='1') then
TEMP<='0';

elsif(J='1' and K='0') then
TEMP<='1';
else
TEMP<= not TEMP;
end if;
end if;
end process;
Q<= TEMP;

end Behavioral;

JK/jk_tb.vhdl
LIBRARY ieee;
USE ieee.std_logic_1164.ALL;
 
-- Uncomment the following library declaration if using
-- arithmetic functions with Signed or Unsigned values
--USE ieee.numeric_std.ALL;
 
ENTITY JK_Flip_Flop_TB IS
END JK_Flip_Flop_TB;
 
ARCHITECTURE behavior OF JK_Flip_Flop_TB IS 
 
    -- Component Declaration for the Unit Under Test (UUT)
 
    COMPONENT JK_Flip_Flop
    PORT(
         J : IN  std_logic;
         K : IN  std_logic;
         CLK : IN  std_logic;
         RST : IN  std_logic;
         Q : OUT  std_logic
        );
    END COMPONENT;
    

   --Inputs
   signal J : std_logic := '0';
   signal K : std_logic := '0';
   signal CLK : std_logic := '0';
   signal RST : std_logic := '0';

 	--Outputs
   signal Q : std_logic;

   -- Clock period definitions
   constant CLK_period : time := 10 ns;
 
BEGIN
 
	-- Instantiate the Unit Under Test (UUT)
   uut: JK_Flip_Flop PORT MAP (
          J => J,
          K => K,
          CLK => CLK,
          RST => RST,
          Q => Q
        );

   -- Clock process definitions
   CLK_process :process
   begin
		CLK <= '0';
		wait for CLK_period/2;
		CLK <= '1';
		wait for CLK_period/2;
   end process;
 

   -- Stimulus process
   stim_proc: process
   begin		
      -- hold reset state for 100 ns.
      wait for 100 ns;	

      --wait for CLK_period*10;

      -- insert stimulus here 
		
		RST<='0';
		CLK<='0';
		wait for 100 ns;
		
		RST<='1';
		CLK<='1';
		J<='0';
		K<='1';
		wait for 100 ns;
		
		J<='0';
		K<='0';
		wait for 100 ns;
		
		J<='1';
		K<='0';
		wait for 100 ns;
		J<='1';
		K<='1';

      wait;
   end process;

END;

JK/result.vcd
$date
  Sat Feb 10 20:37:52 2024
$end
$version
  GHDL v0
$end
$timescale
  1 fs
$end
$scope module standard $end
$upscope $end
$scope module std_logic_1164 $end
$upscope $end
$scope module jk_flip_flop_tb $end
$var reg 1 ! j $end
$var reg 1 " k $end
$var reg 1 # clk $end
$var reg 1 $ rst $end
$var reg 1 % q $end
$scope module uut $end
$var reg 1 & j $end
$var reg 1 ' k $end
$var reg 1 ( clk $end
$var reg 1 ) rst $end
$var reg 1 * q $end
$var reg 1 + temp $end
$upscope $end
$upscope $end
$enddefinitions $end
#0
0!
0"
0#
0$
0%
0&
0'
0(
0)
0*
0+
#5000000
X#
X(
#10000000
0#
0(
#15000000
X#
X(
#20000000
0#
0(
#25000000
X#
X(
#30000000
0#
0(
#35000000
X#
X(
#40000000
0#
0(
#45000000
X#
X(
#50000000
0#
0(
#55000000
X#
X(
#60000000
0#
0(
#65000000
X#
X(
#70000000
0#
0(
#75000000
X#
X(
#80000000
0#
0(
#85000000
X#
X(
#90000000
0#
0(
#95000000
X#
X(
#100000000
0#
0(
#105000000
X#
X(
#110000000
0#
0(
#115000000
X#
X(
#120000000
0#
0(
#125000000
X#
X(
#130000000
0#
0(
#135000000
X#
X(
#140000000
0#
0(
#145000000
X#
X(
#150000000
0#
0(
#155000000
X#
X(
#160000000
0#
0(
#165000000
X#
X(
#170000000
0#
0(
#175000000
X#
X(
#180000000
0#
0(
#185000000
X#
X(
#190000000
0#
0(
#195000000
X#
X(
#200000000
1"
1$
1'
1)
#205000000
1#
1(
#210000000
X#
X(
#215000000
1#
1(
#220000000
X#
X(
#225000000
1#
1(
#230000000
X#
X(
#235000000
1#
1(
#240000000
X#
X(
#245000000
1#
1(
#250000000
X#
X(
#255000000
1#
1(
#260000000
X#
X(
#265000000
1#
1(
#270000000
X#
X(
#275000000
1#
1(
#280000000
X#
X(
#285000000
1#
1(
#290000000
X#
X(
#295000000
1#
1(
#300000000
0"
X#
0'
X(
#305000000
1#
1(
#310000000
X#
X(
#315000000
1#
1(
#320000000
X#
X(
#325000000
1#
1(
#330000000
X#
X(
#335000000
1#
1(
#340000000
X#
X(
#345000000
1#
1(
#350000000
X#
X(
#355000000
1#
1(
#360000000
X#
X(
#365000000
1#
1(
#370000000
X#
X(
#375000000
1#
1(
#380000000
X#
X(
#385000000
1#
1(
#390000000
X#
X(
#395000000
1#
1(
#400000000
1!
X#
1&
X(
#405000000
1#
1%
1(
1*
1+
#410000000
X#
X(
#415000000
1#
1(
#420000000
X#
X(
#425000000
1#
1(
#430000000
X#
X(
#435000000
1#
1(
#440000000
X#
X(
#445000000
1#
1(
#450000000
X#
X(
#455000000
1#
1(
#460000000
X#
X(
#465000000
1#
1(
#470000000
X#
X(
#475000000
1#
1(
#480000000
X#
X(
#485000000
1#
1(
#490000000
X#
X(
#495000000
1#
1(
#500000000
1"
X#
1'
X(
#505000000
1#
0%
1(
0*
0+
#510000000
X#
X(
#515000000
1#
1%
1(
1*
1+
#520000000
X#
X(
#525000000
1#
0%
1(
0*
0+
#530000000
X#
X(
#535000000
1#
1%
1(
1*
1+
#540000000
X#
X(
#545000000
1#
0%
1(
0*
0+
#550000000
X#
X(
#555000000
1#
1%
1(
1*
1+
#560000000
X#
X(
#565000000
1#
0%
1(
0*
0+
#570000000
X#
X(
#575000000
1#
1%
1(
1*
1+
#580000000
X#
X(
#585000000
1#
0%
1(
0*
0+
#590000000
X#
X(
#595000000
1#
1%
1(
1*
1+
#600000000
X#
X(
#605000000
1#
0%
1(
0*
0+
#610000000
X#
X(
#615000000
1#
1%
1(
1*
1+
#620000000
X#
X(
#625000000
1#
0%
1(
0*
0+
#630000000
X#
X(
#635000000
1#
1%
1(
1*
1+
#640000000
X#
X(
#645000000
1#
0%
1(
0*
0+
#650000000
X#
X(
#655000000
1#
1%
1(
1*
1+
#660000000
X#
X(
#665000000
1#
0%
1(
0*
0+
#670000000
X#
X(
#675000000
1#
1%
1(
1*
1+
#680000000
X#
X(
#685000000
1#
0%
1(
0*
0+
#690000000
X#
X(
#695000000
1#
1%
1(
1*
1+
#700000000
X#
X(
#705000000
1#
0%
1(
0*
0+
#710000000
X#
X(
#715000000
1#
1%
1(
1*
1+
#720000000
X#
X(
#725000000
1#
0%
1(
0*
0+
#730000000
X#
X(
#735000000
1#
1%
1(
1*
1+
#740000000
X#
X(
#745000000
1#
0%
1(
0*
0+
#750000000
X#
X(
#755000000
1#
1%
1(
1*
1+
#760000000
X#
X(
#765000000
1#
0%
1(
0*
0+
#770000000
X#
X(
#775000000
1#
1%
1(
1*
1+
#780000000
X#
X(
#785000000
1#
0%
1(
0*
0+
#790000000
X#
X(
#795000000
1#
1%
1(
1*
1+
#800000000
X#
X(
#805000000
1#
0%
1(
0*
0+
#810000000
X#
X(
#815000000
1#
1%
1(
1*
1+
#820000000
X#
X(
#825000000
1#
0%
1(
0*
0+
#830000000
X#
X(
#835000000
1#
1%
1(
1*
1+
#840000000
X#
X(
#845000000
1#
0%
1(
0*
0+
#850000000
X#
X(
#855000000
1#
1%
1(
1*
1+
#860000000
X#
X(
#865000000
1#
0%
1(
0*
0+
#870000000
X#
X(
#875000000
1#
1%
1(
1*
1+
#880000000
X#
X(
#885000000
1#
0%
1(
0*
0+
#890000000
X#
X(
#895000000
1#
1%
1(
1*
1+
#900000000
X#
X(
#905000000
1#
0%
1(
0*
0+
#910000000
X#
X(
#915000000
1#
1%
1(
1*
1+
#920000000
X#
X(
#925000000
1#
0%
1(
0*
0+
#930000000
X#
X(
#935000000
1#
1%
1(
1*
1+
#940000000
X#
X(
#945000000
1#
0%
1(
0*
0+
#950000000
X#
X(
#955000000
1#
1%
1(
1*
1+
#960000000
X#
X(
#965000000
1#
0%
1(
0*
0+
#970000000
X#
X(
#975000000
1#
1%
1(
1*
1+
#980000000
X#
X(
#985000000
1#
0%
1(
0*
0+
#990000000
X#
X(
#995000000
1#
1%
1(
1*
1+
#1000000000
X#
X(
#1005000000
1#
0%
1(
0*
0+
#1010000000
X#
X(
#1015000000
1#
1%
1(
1*
1+
#1020000000
X#
X(
#1025000000
1#
0%
1(
0*
0+
#1030000000
X#
X(
#1035000000
1#
1%
1(
1*
1+
#1040000000
X#
X(
#1045000000
1#
0%
1(
0*
0+
#1050000000
X#
X(
#1055000000
1#
1%
1(
1*
1+
#1060000000
X#
X(
#1065000000
1#
0%
1(
0*
0+
#1070000000
X#
X(
#1075000000
1#
1%
1(
1*
1+
#1080000000
X#
X(
#1085000000
1#
0%
1(
0*
0+
#1090000000
X#
X(
#1095000000
1#
1%
1(
1*
1+
#1100000000
X#
X(
#1105000000
1#
0%
1(
0*
0+
#1110000000
X#
X(
#1115000000
1#
1%
1(
1*
1+
#1120000000
X#
X(
#1125000000
1#
0%
1(
0*
0+
#1130000000
X#
X(
#1135000000
1#
1%
1(
1*
1+
#1140000000
X#
X(
#1145000000
1#
0%
1(
0*
0+
#1150000000
X#
X(
#1155000000
1#
1%
1(
1*
1+
#1160000000
X#
X(
#1165000000
1#
0%
1(
0*
0+
#1170000000
X#
X(
#1175000000
1#
1%
1(
1*
1+
#1180000000
X#
X(
#1185000000
1#
0%
1(
0*
0+
#1190000000
X#
X(
#1195000000
1#
1%
1(
1*
1+
#1200000000
X#
X(
#1205000000
1#
0%
1(
0*
0+
#1210000000
X#
X(
#1215000000
1#
1%
1(
1*
1+
#1220000000
X#
X(
#1225000000
1#
0%
1(
0*
0+
#1230000000
X#
X(
#1235000000
1#
1%
1(
1*
1+
#1240000000
X#
X(
#1245000000
1#
0%
1(
0*
0+
#1250000000
X#
X(
#1255000000
1#
1%
1(
1*
1+
#1260000000
X#
X(
#1265000000
1#
0%
1(
0*
0+
#1270000000
X#
X(
#1275000000
1#
1%
1(
1*
1+
#1280000000
X#
X(
#1285000000
1#
0%
1(
0*
0+
#1290000000
X#
X(
#1295000000
1#
1%
1(
1*
1+
#1300000000
X#
X(
#1305000000
1#
0%
1(
0*
0+
#1310000000
X#
X(
#1315000000
1#
1%
1(
1*
1+
#1320000000
X#
X(
#1325000000
1#
0%
1(
0*
0+
#1330000000
X#
X(
#1335000000
1#
1%
1(
1*
1+
#1340000000
X#
X(
#1345000000
1#
0%
1(
0*
0+
#1350000000
X#
X(
#1355000000
1#
1%
1(
1*
1+
#1360000000
X#
X(
#1365000000
1#
0%
1(
0*
0+
#1370000000
X#
X(
#1375000000
1#
1%
1(
1*
1+
#1380000000
X#
X(
#1385000000
1#
0%
1(
0*
0+
#1390000000
X#
X(
#1395000000
1#
1%
1(
1*
1+
#1400000000
X#
X(
#1405000000
1#
0%
1(
0*
0+
#1410000000
X#
X(
#1415000000
1#
1%
1(
1*
1+
#1420000000
X#
X(
#1425000000
1#
0%
1(
0*
0+
#1430000000
X#
X(
#1435000000
1#
1%
1(
1*
1+
#1440000000
X#
X(
#1445000000
1#
0%
1(
0*
0+
#1450000000
X#
X(
#1455000000
1#
1%
1(
1*
1+
#1460000000
X#
X(
#1465000000
1#
0%
1(
0*
0+
#1470000000
X#
X(
#1475000000
1#
1%
1(
1*
1+
#1480000000
X#
X(
#1485000000
1#
0%
1(
0*
0+
#1490000000
X#
X(
#1495000000
1#
1%
1(
1*
1+
#1500000000
X#
X(
#1505000000
1#
0%
1(
0*
0+
#1510000000
X#
X(
#1515000000
1#
1%
1(
1*
1+
#1520000000
X#
X(
#1525000000
1#
0%
1(
0*
0+
#1530000000
X#
X(
#1535000000
1#
1%
1(
1*
1+
#1540000000
X#
X(
#1545000000
1#
0%
1(
0*
0+
#1550000000
X#
X(
#1555000000
1#
1%
1(
1*
1+
#1560000000
X#
X(
#1565000000
1#
0%
1(
0*
0+
#1570000000
X#
X(
#1575000000
1#
1%
1(
1*
1+
#1580000000
X#
X(
#1585000000
1#
0%
1(
0*
0+
#1590000000
X#
X(
#1595000000
1#
1%
1(
1*
1+
#1600000000
X#
X(
#1605000000
1#
0%
1(
0*
0+
#1610000000
X#
X(
#1615000000
1#
1%
1(
1*
1+
#1620000000
X#
X(
#1625000000
1#
0%
1(
0*
0+
#1630000000
X#
X(
#1635000000
1#
1%
1(
1*
1+
#1640000000
X#
X(
#1645000000
1#
0%
1(
0*
0+
#1650000000
X#
X(
#1655000000
1#
1%
1(
1*
1+
#1660000000
X#
X(
#1665000000
1#
0%
1(
0*
0+
#1670000000
X#
X(
#1675000000
1#
1%
1(
1*
1+
#1680000000
X#
X(
#1685000000
1#
0%
1(
0*
0+
#1690000000
X#
X(
#1695000000
1#
1%
1(
1*
1+
#1700000000
X#
X(
#1705000000
1#
0%
1(
0*
0+
#1710000000
X#
X(
#1715000000
1#
1%
1(
1*
1+
#1720000000
X#
X(
#1725000000
1#
0%
1(
0*
0+
#1730000000
X#
X(
#1735000000
1#
1%
1(
1*
1+
#1740000000
X#
X(
#1745000000
1#
0%
1(
0*
0+
#1750000000
X#
X(
#1755000000
1#
1%
1(
1*
1+
#1760000000
X#
X(
#1765000000
1#
0%
1(
0*
0+
#1770000000
X#
X(
#1775000000
1#
1%
1(
1*
1+
#1780000000
X#
X(
#1785000000
1#
0%
1(
0*
0+
#1790000000
X#
X(
#1795000000
1#
1%
1(
1*
1+
#1800000000
X#
X(
#1805000000
1#
0%
1(
0*
0+
#1810000000
X#
X(
#1815000000
1#
1%
1(
1*
1+
#1820000000
X#
X(
#1825000000
1#
0%
1(
0*
0+
#1830000000
X#
X(
#1835000000
1#
1%
1(
1*
1+
#1840000000
X#
X(
#1845000000
1#
0%
1(
0*
0+
#1850000000
X#
X(
#1855000000
1#
1%
1(
1*
1+
#1860000000
X#
X(
#1865000000
1#
0%
1(
0*
0+
#1870000000
X#
X(
#1875000000
1#
1%
1(
1*
1+
#1880000000
X#
X(
#1885000000
1#
0%
1(
0*
0+
#1890000000
X#
X(
#1895000000
1#
1%
1(
1*
1+
#1900000000
X#
X(
#1905000000
1#
0%
1(
0*
0+
#1910000000
X#
X(
#1915000000
1#
1%
1(
1*
1+
#1920000000
X#
X(
#1925000000
1#
0%
1(
0*
0+
#1930000000
X#
X(
#1935000000
1#
1%
1(
1*
1+
#1940000000
X#
X(
#1945000000
1#
0%
1(
0*
0+
#1950000000
X#
X(
#1955000000
1#
1%
1(
1*
1+
#1960000000
X#
X(
#1965000000
1#
0%
1(
0*
0+
#1970000000
X#
X(
#1975000000
1#
1%
1(
1*
1+
#1980000000
X#
X(
#1985000000
1#
0%
1(
0*
0+
#1990000000
X#
X(
#1995000000
1#
1%
1(
1*
1+
#2000000000
X#
X(
#2005000000
1#
0%
1(
0*
0+
#2010000000
X#
X(
#2015000000
1#
1%
1(
1*
1+
#2020000000
X#
X(
#2025000000
1#
0%
1(
0*
0+
#2030000000
X#
X(
#2035000000
1#
1%
1(
1*
1+
#2040000000
X#
X(
#2045000000
1#
0%
1(
0*
0+
#2050000000
X#
X(
#2055000000
1#
1%
1(
1*
1+
#2060000000
X#
X(
#2065000000
1#
0%
1(
0*
0+
#2070000000
X#
X(
#2075000000
1#
1%
1(
1*
1+
#2080000000
X#
X(
#2085000000
1#
0%
1(
0*
0+
#2090000000
X#
X(
#2095000000
1#
1%
1(
1*
1+
#2100000000
X#
X(
#2105000000
1#
0%
1(
0*
0+
#2110000000
X#
X(
#2115000000
1#
1%
1(
1*
1+
#2120000000
X#
X(
#2125000000
1#
0%
1(
0*
0+
#2130000000
X#
X(
#2135000000
1#
1%
1(
1*
1+
#2140000000
X#
X(
#2145000000
1#
0%
1(
0*
0+
#2150000000
X#
X(
#2155000000
1#
1%
1(
1*
1+
#2160000000
X#
X(
#2165000000
1#
0%
1(
0*
0+
#2170000000
X#
X(
#2175000000
1#
1%
1(
1*
1+
#2180000000
X#
X(
#2185000000
1#
0%
1(
0*
0+
#2190000000
X#
X(
#2195000000
1#
1%
1(
1*
1+
#2200000000
X#
X(
#2205000000
1#
0%
1(
0*
0+
#2210000000
X#
X(
#2215000000
1#
1%
1(
1*
1+
#2220000000
X#
X(
#2225000000
1#
0%
1(
0*
0+
#2230000000
X#
X(
#2235000000
1#
1%
1(
1*
1+
#2240000000
X#
X(
#2245000000
1#
0%
1(
0*
0+
#2250000000
X#
X(
#2255000000
1#
1%
1(
1*
1+
#2260000000
X#
X(
#2265000000
1#
0%
1(
0*
0+
#2270000000
X#
X(
#2275000000
1#
1%
1(
1*
1+
#2280000000
X#
X(
#2285000000
1#
0%
1(
0*
0+
#2290000000
X#
X(
#2295000000
1#
1%
1(
1*
1+
#2300000000
X#
X(
#2305000000
1#
0%
1(
0*
0+
#2310000000
X#
X(
#2315000000
1#
1%
1(
1*
1+
#2320000000
X#
X(
#2325000000
1#
0%
1(
0*
0+
#2330000000
X#
X(
#2335000000
1#
1%
1(
1*
1+
#2340000000
X#
X(
#2345000000
1#
0%
1(
0*
0+
#2350000000
X#
X(
#2355000000
1#
1%
1(
1*
1+
#2360000000
X#
X(
#2365000000
1#
0%
1(
0*
0+
#2370000000
X#
X(
#2375000000
1#
1%
1(
1*
1+
#2380000000
X#
X(
#2385000000
1#
0%
1(
0*
0+
#2390000000
X#
X(
#2395000000
1#
1%
1(
1*
1+
#2400000000
X#
X(
#2405000000
1#
0%
1(
0*
0+
#2410000000
X#
X(
#2415000000
1#
1%
1(
1*
1+
#2420000000
X#
X(
#2425000000
1#
0%
1(
0*
0+
#2430000000
X#
X(
#2435000000
1#
1%
1(
1*
1+
#2440000000
X#
X(
#2445000000
1#
0%
1(
0*
0+
#2450000000
X#
X(
#2455000000
1#
1%
1(
1*
1+
#2460000000
X#
X(
#2465000000
1#
0%
1(
0*
0+
#2470000000
X#
X(
#2475000000
1#
1%
1(
1*
1+
#2480000000
X#
X(
#2485000000
1#
0%
1(
0*
0+
#2490000000
X#
X(
#2495000000
1#
1%
1(
1*
1+
#2500000000
X#
X(
#2505000000
1#
0%
1(
0*
0+
#2510000000
X#
X(
#2515000000
1#
1%
1(
1*
1+
#2520000000
X#
X(
#2525000000
1#
0%
1(
0*
0+
#2530000000
X#
X(
#2535000000
1#
1%
1(
1*
1+
#2540000000
X#
X(
#2545000000
1#
0%
1(
0*
0+
#2550000000
X#
X(
#2555000000
1#
1%
1(
1*
1+
#2560000000
X#
X(
#2565000000
1#
0%
1(
0*
0+
#2570000000
X#
X(
#2575000000
1#
1%
1(
1*
1+
#2580000000
X#
X(
#2585000000
1#
0%
1(
0*
0+
#2590000000
X#
X(
#2595000000
1#
1%
1(
1*
1+
#2600000000
X#
X(
#2605000000
1#
0%
1(
0*
0+
#2610000000
X#
X(
#2615000000
1#
1%
1(
1*
1+
#2620000000
X#
X(
#2625000000
1#
0%
1(
0*
0+
#2630000000
X#
X(
#2635000000
1#
1%
1(
1*
1+
#2640000000
X#
X(
#2645000000
1#
0%
1(
0*
0+
#2650000000
X#
X(
#2655000000
1#
1%
1(
1*
1+
#2660000000
X#
X(
#2665000000
1#
0%
1(
0*
0+
#2670000000
X#
X(
#2675000000
1#
1%
1(
1*
1+
#2680000000
X#
X(
#2685000000
1#
0%
1(
0*
0+
#2690000000
X#
X(
#2695000000
1#
1%
1(
1*
1+
#2700000000
X#
X(
#2705000000
1#
0%
1(
0*
0+
#2710000000
X#
X(
#2715000000
1#
1%
1(
1*
1+
#2720000000
X#
X(
#2725000000
1#
0%
1(
0*
0+
#2730000000
X#
X(
#2735000000
1#
1%
1(
1*
1+
#2740000000
X#
X(
#2745000000
1#
0%
1(
0*
0+
#2750000000
X#
X(
#2755000000
1#
1%
1(
1*
1+
#2760000000
X#
X(
#2765000000
1#
0%
1(
0*
0+
#2770000000
X#
X(
#2775000000
1#
1%
1(
1*
1+
#2780000000
X#
X(
#2785000000
1#
0%
1(
0*
0+
#2790000000
X#
X(
#2795000000
1#
1%
1(
1*
1+
#2800000000
X#
X(
#2805000000
1#
0%
1(
0*
0+
#2810000000
X#
X(
#2815000000
1#
1%
1(
1*
1+
#2820000000
X#
X(
#2825000000
1#
0%
1(
0*
0+
#2830000000
X#
X(
#2835000000
1#
1%
1(
1*
1+
#2840000000
X#
X(
#2845000000
1#
0%
1(
0*
0+
#2850000000
X#
X(
#2855000000
1#
1%
1(
1*
1+
#2860000000
X#
X(
#2865000000
1#
0%
1(
0*
0+
#2870000000
X#
X(
#2875000000
1#
1%
1(
1*
1+
#2880000000
X#
X(
#2885000000
1#
0%
1(
0*
0+
#2890000000
X#
X(
#2895000000
1#
1%
1(
1*
1+
#2900000000
X#
X(
#2905000000
1#
0%
1(
0*
0+
#2910000000
X#
X(
#2915000000
1#
1%
1(
1*
1+
#2920000000
X#
X(
#2925000000
1#
0%
1(
0*
0+
#2930000000
X#
X(
#2935000000
1#
1%
1(
1*
1+
#2940000000
X#
X(
#2945000000
1#
0%
1(
0*
0+
#2950000000
X#
X(
#2955000000
1#
1%
1(
1*
1+
#2960000000
X#
X(
#2965000000
1#
0%
1(
0*
0+
#2970000000
X#
X(
#2975000000
1#
1%
1(
1*
1+
#2980000000
X#
X(
#2985000000
1#
0%
1(
0*
0+
#2990000000
X#
X(
#2995000000
1#
1%
1(
1*
1+
#3000000000
X#
X(
#3005000000
1#
0%
1(
0*
0+
#3010000000
X#
X(
#3015000000
1#
1%
1(
1*
1+
#3020000000
X#
X(
#3025000000
1#
0%
1(
0*
0+
#3030000000
X#
X(
#3035000000
1#
1%
1(
1*
1+
#3040000000
X#
X(
#3045000000
1#
0%
1(
0*
0+
#3050000000
X#
X(
#3055000000
1#
1%
1(
1*
1+
#3060000000
X#
X(
#3065000000
1#
0%
1(
0*
0+
#3070000000
X#
X(
#3075000000
1#
1%
1(
1*
1+
#3080000000
X#
X(
#3085000000
1#
0%
1(
0*
0+
#3090000000
X#
X(
#3095000000
1#
1%
1(
1*
1+
#3100000000
X#
X(
#3105000000
1#
0%
1(
0*
0+
#3110000000
X#
X(
#3115000000
1#
1%
1(
1*
1+
#3120000000
X#
X(
#3125000000
1#
0%
1(
0*
0+
#3130000000
X#
X(
#3135000000
1#
1%
1(
1*
1+
#3140000000
X#
X(
#3145000000
1#
0%
1(
0*
0+
#3150000000
X#
X(
#3155000000
1#
1%
1(
1*
1+
#3160000000
X#
X(
#3165000000
1#
0%
1(
0*
0+
#3170000000
X#
X(
#3175000000
1#
1%
1(
1*
1+
#3180000000
X#
X(
#3185000000
1#
0%
1(
0*
0+
#3190000000
X#
X(
#3195000000
1#
1%
1(
1*
1+
#3200000000
X#
X(
#3205000000
1#
0%
1(
0*
0+
#3210000000
X#
X(
#3215000000
1#
1%
1(
1*
1+
#3220000000
X#
X(
#3225000000
1#
0%
1(
0*
0+
#3230000000
X#
X(
#3235000000
1#
1%
1(
1*
1+
#3240000000
X#
X(
#3245000000
1#
0%
1(
0*
0+
#3250000000
X#
X(
#3255000000
1#
1%
1(
1*
1+
#3260000000
X#
X(
#3265000000
1#
0%
1(
0*
0+
#3270000000
X#
X(
#3275000000
1#
1%
1(
1*
1+
#3280000000
X#
X(
#3285000000
1#
0%
1(
0*
0+
#3290000000
X#
X(
#3295000000
1#
1%
1(
1*
1+
#3300000000
X#
X(
#3305000000
1#
0%
1(
0*
0+
#3310000000
X#
X(
#3315000000
1#
1%
1(
1*
1+
#3320000000
X#
X(
#3325000000
1#
0%
1(
0*
0+
#3330000000
X#
X(
#3335000000
1#
1%
1(
1*
1+
#3340000000
X#
X(
#3345000000
1#
0%
1(
0*
0+
#3350000000
X#
X(
#3355000000
1#
1%
1(
1*
1+
#3360000000
X#
X(
#3365000000
1#
0%
1(
0*
0+
#3370000000
X#
X(
#3375000000
1#
1%
1(
1*
1+
#3380000000
X#
X(
#3385000000
1#
0%
1(
0*
0+
#3390000000
X#
X(
#3395000000
1#
1%
1(
1*
1+
#3400000000
X#
X(
#3405000000
1#
0%
1(
0*
0+
#3410000000
X#
X(
#3415000000
1#
1%
1(
1*
1+
#3420000000
X#
X(
#3425000000
1#
0%
1(
0*
0+
#3430000000
X#
X(
#3435000000
1#
1%
1(
1*
1+
#3440000000
X#
X(
#3445000000
1#
0%
1(
0*
0+
#3450000000
X#
X(
#3455000000
1#
1%
1(
1*
1+
#3460000000
X#
X(
#3465000000
1#
0%
1(
0*
0+
#3470000000
X#
X(
#3475000000
1#
1%
1(
1*
1+
#3480000000
X#
X(
#3485000000
1#
0%
1(
0*
0+
#3490000000
X#
X(
#3495000000
1#
1%
1(
1*
1+
#3500000000
X#
X(
#3505000000
1#
0%
1(
0*
0+
#3510000000
X#
X(
#3515000000
1#
1%
1(
1*
1+
#3520000000
X#
X(
#3525000000
1#
0%
1(
0*
0+
#3530000000
X#
X(
#3535000000
1#
1%
1(
1*
1+
#3540000000
X#
X(
#3545000000
1#
0%
1(
0*
0+
#3550000000
X#
X(
#3555000000
1#
1%
1(
1*
1+
#3560000000
X#
X(
#3565000000
1#
0%
1(
0*
0+
#3570000000
X#
X(
#3575000000
1#
1%
1(
1*
1+
#3580000000
X#
X(
#3585000000
1#
0%
1(
0*
0+
#3590000000
X#
X(
#3595000000
1#
1%
1(
1*
1+
#3600000000
X#
X(
#3605000000
1#
0%
1(
0*
0+
#3610000000
X#
X(
#3615000000
1#
1%
1(
1*
1+
#3620000000
X#
X(
#3625000000
1#
0%
1(
0*
0+
#3630000000
X#
X(
#3635000000
1#
1%
1(
1*
1+
#3640000000
X#
X(
#3645000000
1#
0%
1(
0*
0+
#3650000000
X#
X(
#3655000000
1#
1%
1(
1*
1+
#3660000000
X#
X(
#3665000000
1#
0%
1(
0*
0+
#3670000000
X#
X(
#3675000000
1#
1%
1(
1*
1+
#3680000000
X#
X(
#3685000000
1#
0%
1(
0*
0+
#3690000000
X#
X(
#3695000000
1#
1%
1(
1*
1+
#3700000000
X#
X(
#3705000000
1#
0%
1(
0*
0+
#3710000000
X#
X(
#3715000000
1#
1%
1(
1*
1+
#3720000000
X#
X(
#3725000000
1#
0%
1(
0*
0+
#3730000000
X#
X(
#3735000000
1#
1%
1(
1*
1+
#3740000000
X#
X(
#3745000000
1#
0%
1(
0*
0+
#3750000000
X#
X(
#3755000000
1#
1%
1(
1*
1+
#3760000000
X#
X(
#3765000000
1#
0%
1(
0*
0+
#3770000000
X#
X(
#3775000000
1#
1%
1(
1*
1+
#3780000000
X#
X(
#3785000000
1#
0%
1(
0*
0+
#3790000000
X#
X(
#3795000000
1#
1%
1(
1*
1+
#3800000000
X#
X(
#3805000000
1#
0%
1(
0*
0+
#3810000000
X#
X(
#3815000000
1#
1%
1(
1*
1+
#3820000000
X#
X(
#3825000000
1#
0%
1(
0*
0+
#3830000000
X#
X(
#3835000000
1#
1%
1(
1*
1+
#3840000000
X#
X(
#3845000000
1#
0%
1(
0*
0+
#3850000000
X#
X(
#3855000000
1#
1%
1(
1*
1+
#3860000000
X#
X(
#3865000000
1#
0%
1(
0*
0+
#3870000000
X#
X(
#3875000000
1#
1%
1(
1*
1+
#3880000000
X#
X(
#3885000000
1#
0%
1(
0*
0+
#3890000000
X#
X(
#3895000000
1#
1%
1(
1*
1+
#3900000000
X#
X(
#3905000000
1#
0%
1(
0*
0+
#3910000000
X#
X(
#3915000000
1#
1%
1(
1*
1+
#3920000000
X#
X(
#3925000000
1#
0%
1(
0*
0+
#3930000000
X#
X(
#3935000000
1#
1%
1(
1*
1+
#3940000000
X#
X(
#3945000000
1#
0%
1(
0*
0+
#3950000000
X#
X(
#3955000000
1#
1%
1(
1*
1+
#3960000000
X#
X(
#3965000000
1#
0%
1(
0*
0+
#3970000000
X#
X(
#3975000000
1#
1%
1(
1*
1+
#3980000000
X#
X(
#3985000000
1#
0%
1(
0*
0+
#3990000000
X#
X(
#3995000000
1#
1%
1(
1*
1+
#4000000000
X#
X(
#4005000000
1#
0%
1(
0*
0+
#4010000000
X#
X(
#4015000000
1#
1%
1(
1*
1+
#4020000000
X#
X(
#4025000000
1#
0%
1(
0*
0+
#4030000000
X#
X(
#4035000000
1#
1%
1(
1*
1+
#4040000000
X#
X(
#4045000000
1#
0%
1(
0*
0+
#4050000000
X#
X(
#4055000000
1#
1%
1(
1*
1+
#4060000000
X#
X(
#4065000000
1#
0%
1(
0*
0+
#4070000000
X#
X(
#4075000000
1#
1%
1(
1*
1+
#4080000000
X#
X(
#4085000000
1#
0%
1(
0*
0+
#4090000000
X#
X(
#4095000000
1#
1%
1(
1*
1+
#4100000000
X#
X(
#4105000000
1#
0%
1(
0*
0+
#4110000000
X#
X(
#4115000000
1#
1%
1(
1*
1+
#4120000000
X#
X(
#4125000000
1#
0%
1(
0*
0+
#4130000000
X#
X(
#4135000000
1#
1%
1(
1*
1+
#4140000000
X#
X(
#4145000000
1#
0%
1(
0*
0+
#4150000000
X#
X(
#4155000000
1#
1%
1(
1*
1+
#4160000000
X#
X(
#4165000000
1#
0%
1(
0*
0+
#4170000000
X#
X(
#4175000000
1#
1%
1(
1*
1+
#4180000000
X#
X(
#4185000000
1#
0%
1(
0*
0+
#4190000000
X#
X(
#4195000000
1#
1%
1(
1*
1+
#4200000000
X#
X(
#4205000000
1#
0%
1(
0*
0+
#4210000000
X#
X(
#4215000000
1#
1%
1(
1*
1+
#4220000000
X#
X(
#4225000000
1#
0%
1(
0*
0+
#4230000000
X#
X(
#4235000000
1#
1%
1(
1*
1+
#4240000000
X#
X(
#4245000000
1#
0%
1(
0*
0+
#4250000000
X#
X(
#4255000000
1#
1%
1(
1*
1+
#4260000000
X#
X(
#4265000000
1#
0%
1(
0*
0+
#4270000000
X#
X(
