fulladder_with_halfadder/Half_adder.vhdl
library IEEE;
use IEEE.STD_LOGIC_1164.ALL;

entity HA is
    Port (
        A, B : in  STD_LOGIC;
        Sum, CarryOut : out STD_LOGIC
    );
end HA;

architecture dataflow of HA is
begin
    Sum <= A XOR B;
    CarryOut <= A AND B;
end dataflow;

fulladder_with_halfadder/full_adder_component.vhdl
library IEEE;
use IEEE.STD_LOGIC_1164.ALL;

entity FA is
    Port (
        A, B, Cin : in  STD_LOGIC;
        Sum, Cout : out STD_LOGIC
    );
end FA;

architecture structural of FA is
    component HA is
        Port (
            A, B : in  STD_LOGIC;
            Sum, CarryOut : out STD_LOGIC
        );
    end component;
    
    signal S0, S1, S2 : STD_LOGIC;
begin
    U1: HA PORT MAP(A => A, B => B, Sum => S0, CarryOut => S1);
    U2: HA PORT MAP(A => S0, B => Cin, Sum => Sum, CarryOut => S2);
    Cout <= S1 OR S2;
end structural;

fulladder_with_halfadder/full_adder_HA_TB.vhdl
library IEEE;
use IEEE.STD_LOGIC_1164.ALL;

entity FAdder_TB is
end FAdder_TB;

architecture behavior of FAdder_TB is
    signal A, B, Cin, Sum, Cout : STD_LOGIC;
    
    -- Define a clock period
    constant CLK_PERIOD : time :=  10 ns;
begin
    -- Instantiate the unit under test (UUT)
    UUT: entity work.FA
        port map (
            A => A,
            B => B,
            Cin => Cin,
            Sum => Sum,
            Cout => Cout
        );

    -- Stimulus process
    stim_proc: process
    begin
        -- Hold reset state
        A <= '0';
        B <= '0';
        Cin <= '0';
        wait for CLK_PERIOD;
        
        -- Provide inputs for different cases
        A <= '0'; B <= '0'; Cin <= '0'; wait for CLK_PERIOD;
        A <= '0'; B <= '0'; Cin <= '1'; wait for CLK_PERIOD;
        A <= '0'; B <= '1'; Cin <= '0'; wait for CLK_PERIOD;
        A <= '0'; B <= '1'; Cin <= '1'; wait for CLK_PERIOD;
        A <= '1'; B <= '0'; Cin <= '0'; wait for CLK_PERIOD;
        A <= '1'; B <= '0'; Cin <= '1'; wait for CLK_PERIOD;
        A <= '1'; B <= '1'; Cin <= '0'; wait for CLK_PERIOD;
        A <= '1'; B <= '1'; Cin <= '1'; wait for CLK_PERIOD;
        
        -- Stop the simulation
        wait;
    end process;
end behavior;

fulladder_with_halfadder/result.vcd
$date
  Tue Feb 20 19:02:03 2024
$end
$version
  GHDL v0
$end
$timescale
  1 fs
$end
$scope module standard $end
$upscope $end
$scope module std_logic_1164 $end
$upscope $end
$scope module fadder_tb $end
$var reg 1 ! a $end
$var reg 1 " b $end
$var reg 1 # cin $end
$var reg 1 $ sum $end
$var reg 1 % cout $end
$scope module uut $end
$var reg 1 & a $end
$var reg 1 ' b $end
$var reg 1 ( cin $end
$var reg 1 ) sum $end
$var reg 1 * cout $end
$var reg 1 + s0 $end
$var reg 1 , s1 $end
$var reg 1 - s2 $end
$scope module u1 $end
$var reg 1 . a $end
$var reg 1 / b $end
$var reg 1 0 sum $end
$var reg 1 1 carryout $end
$upscope $end
$scope module u2 $end
$var reg 1 2 a $end
$var reg 1 3 b $end
$var reg 1 4 sum $end
$var reg 1 5 carryout $end
$upscope $end
$upscope $end
$upscope $end
$enddefinitions $end
#0
0!
0"
0#
0$
0%
0&
0'
0(
0)
0*
0+
0,
0-
0.
0/
00
01
02
03
04
05
#10000000
#20000000
1#
1$
1(
1)
13
14
#30000000
1"
0#
1$
1'
0(
1)
1+
1/
10
12
03
14
#40000000
1#
0$
1%
1(
0)
1*
1-
13
04
15
#50000000
1!
0"
0#
1$
0%
1&
0'
0(
1)
0*
0-
1.
0/
03
14
05
#60000000
1#
0$
1%
1(
0)
1*
1-
13
04
15
#70000000
1"
0#
0$
1'
0(
0)
0+
1,
0-
1/
00
11
02
03
04
05
#80000000
1#
1$
1(
1)
13
14
