sequence_detector/seq_det.vhdl
-- Sequence Detector: Detects the sequence "1011"

library IEEE;
use IEEE.STD_LOGIC_1164.ALL;
use IEEE.NUMERIC_STD.ALL;

entity Sequence_Detector is
    Port (
        clk: in STD_LOGIC;
        reset: in STD_LOGIC;
        input_bit: in STD_LOGIC;
        sequence_detected: out STD_LOGIC
    );
end Sequence_Detector;

architecture Behavioral of Sequence_Detector is
    -- State type definition
    type state_type is (S0, S1, S2, S3);
    signal current_state, next_state: state_type;
begin
    -- State transition process
    process(clk, reset)
    begin
        if reset = '1' then
            current_state <= S0;
        elsif rising_edge(clk) then
            current_state <= next_state;
        end if;
    end process;

    -- Next state logic and sequence detection
    process(current_state, input_bit)
    begin
        next_state <= current_state;
        sequence_detected <= '0';

        case current_state is
            when S0 =>
                if input_bit = '1' then
                    next_state <= S1;
                end if;
            when S1 =>
                if input_bit = '0' then
                    next_state <= S2;
                end if;
            when S2 =>
                if input_bit = '1' then
                    next_state <= S3;
                else
                    next_state <= S0;
                end if;
            when S3 =>
                if input_bit = '1' then
                    sequence_detected <= '1';
                    next_state <= S1;
                else
                    next_state <= S0;
                end if;
            when others =>
                next_state <= S0;
        end case;
    end process;
end Behavioral;

sequence_detector/seq_det_tb.vhdl
library IEEE;
use IEEE.STD_LOGIC_1164.ALL;

entity Sequence_Detector_Testbench is
end Sequence_Detector_Testbench;

architecture Behavioral of Sequence_Detector_Testbench is
    component Sequence_Detector is
        Port (
            clk: in STD_LOGIC;
            reset: in STD_LOGIC;
            input_bit: in STD_LOGIC;
            sequence_detected: out STD_LOGIC
        );
    end component;

    signal clk: STD_LOGIC := '0';
    signal reset: STD_LOGIC := '0';
    signal input_bit: STD_LOGIC;
    signal sequence_detected: STD_LOGIC;
begin
    -- Instantiate the sequence detector
    UUT: Sequence_Detector
        port map (
            clk => clk,
            reset => reset,
            input_bit => input_bit,
            sequence_detected => sequence_detected
        );

    -- Clock process
    clk_process: process
    begin
        while now < 100 ns loop
            clk <= '0';
            wait for 5 ns;
            clk <= '1';
            wait for 5 ns;
        end loop;
        wait;
    end process;

    -- Stimulus process
    stim_proc: process
    begin
        reset <= '1';
        wait for 10 ns;
        reset <= '0';
        
        -- Stimulate the input sequence
        input_bit <= '1'; wait for 10 ns;
        input_bit <= '0'; wait for 10 ns;
        input_bit <= '1'; wait for 10 ns;
        input_bit <= '1'; wait for 10 ns;
        input_bit <= '0'; wait for 10 ns;
        input_bit <= '1'; wait for 10 ns;
        input_bit <= '0'; wait for 10 ns;
        input_bit <= '1'; wait for 10 ns;
        input_bit <= '1'; wait for 10 ns;
        input_bit <= '1'; wait for 10 ns;

        wait;
    end process;
end Behavioral;

sequence_detector/result.vcd
$date
  Sat Feb 10 09:56:41 2024
$end
$version
  GHDL v0
$end
$timescale
  1 fs
$end
$scope module standard $end
$upscope $end
$scope module std_logic_1164 $end
$upscope $end
$scope module numeric_std $end
$upscope $end
$scope module sequence_detector_testbench $end
$var reg 1 ! clk $end
$var reg 1 " reset $end
$var reg 1 # input_bit $end
$var reg 1 $ sequence_detected $end
$scope module uut $end
$var reg 1 % clk $end
$var reg 1 & reset $end
$var reg 1 ' input_bit $end
$var reg 1 ( sequence_detected $end
$comment current_state is not handled $end
$comment next_state is not handled $end
$upscope $end
$upscope $end
$enddefinitions $end
#0
0!
1"
U#
0$
0%
1&
U'
0(
#5000000
1!
1%
#10000000
0!
0"
1#
0%
0&
1'
#15000000
1!
1%
#20000000
0!
0#
0%
0'
#25000000
1!
1%
#30000000
0!
1#
0%
1'
#35000000
1!
1$
1%
1(
#40000000
0!
0%
#45000000
1!
0$
1%
0(
#50000000
0!
0#
0%
0'
#55000000
1!
1%
#60000000
0!
1#
0%
1'
#65000000
1!
1$
1%
1(
#70000000
0!
0#
0$
0%
0'
0(
#75000000
1!
1%
#80000000
0!
1#
0%
1'
